README.txt
setup.cfg
setup.py
collective/__init__.py
collective/__init__.pyc
collective.prettysociable.egg-info/PKG-INFO
collective.prettysociable.egg-info/SOURCES.txt
collective.prettysociable.egg-info/dependency_links.txt
collective.prettysociable.egg-info/entry_points.txt
collective.prettysociable.egg-info/namespace_packages.txt
collective.prettysociable.egg-info/not-zip-safe
collective.prettysociable.egg-info/paster_plugins.txt
collective.prettysociable.egg-info/requires.txt
collective.prettysociable.egg-info/top_level.txt
collective/prettysociable/__init__.py
collective/prettysociable/configure.zcml
collective/prettysociable/exportimport.py
collective/prettysociable/interfaces.py
collective/prettysociable/migration.py
collective/prettysociable/tests.py
collective/prettysociable/browser/__init__.py
collective/prettysociable/browser/configure.zcml
collective/prettysociable/browser/view.py
collective/prettysociable/browser/css/prettySociable.css
collective/prettysociable/browser/images/delicious.png
collective/prettysociable/browser/images/digg.png
collective/prettysociable/browser/images/facebook.png
collective/prettysociable/browser/images/linkedin.png
collective/prettysociable/browser/images/reddit.png
collective/prettysociable/browser/images/stumbleupon.png
collective/prettysociable/browser/images/tumblr.png
collective/prettysociable/browser/images/twitter.png
collective/prettysociable/browser/images/backgrounds/bl.png
collective/prettysociable/browser/images/backgrounds/br.png
collective/prettysociable/browser/images/backgrounds/cl.png
collective/prettysociable/browser/images/backgrounds/cr.png
collective/prettysociable/browser/images/backgrounds/tl.png
collective/prettysociable/browser/images/backgrounds/tr.png
collective/prettysociable/browser/images/backgrounds/tt_l.png
collective/prettysociable/browser/images/backgrounds/tt_r.png
collective/prettysociable/browser/javascript/jquery.prettySociable.compressed.js
collective/prettysociable/browser/javascript/jquery.prettySociable.js
collective/prettysociable/browser/javascript/jquery.url.packed.js
collective/prettysociable/profiles/default/browserlayer.xml
collective/prettysociable/profiles/default/collective.prettysociable.txt
collective/prettysociable/profiles/default/cssregistry.xml
collective/prettysociable/profiles/default/jsregistry.xml
collective/prettysociable/profiles/default/metadata.xml
