Metadata-Version: 1.0
Name: collective.prettysociable
Version: 0.3.1
Summary: prettySociable integration for Plone.
Home-page: http://svn.plone.org/svn/collective/collective.prettysociable
Author: Thomas Massmann
Author-email: thomas.massmann@inqbus.de
License: GPL
Keywords: Plone SocialMedia Web Links
Platform: UNKNOWN
Classifier: Framework :: Plone
Classifier: Programming Language :: Python
